msal_streamlit_t2/__init__.py
msal_streamlit_t2/frontend/dist/assets/index-297265e4.css
msal_streamlit_t2/frontend/dist/assets/index-b8710480.js
msal_streamlit_t2/frontend/dist/index.html
msal_streamlit_t2/test_run.py
msal_streamlit_t2-1.1.5.dist-info/LICENSE
msal_streamlit_t2-1.1.5.dist-info/METADATA
msal_streamlit_t2-1.1.5.dist-info/WHEEL
msal_streamlit_t2-1.1.5.dist-info/RECORD
